Metadata-Version: 2.1
Name: bibtextidying
Version: 0.1.0
Summary: Help to use bib_file more easily
Home-page: UNKNOWN
Author: Jian Ding and ShiBo Xu and Kun Chen
Author-email: 937207118@qq.com
License: MIT
Platform: UNKNOWN
License-File: LICENSE.txt
